mince/__init__.py
mince/__main__.py
mince/py.typed
mince/types.py
mince/cli/__init__.py
mince/cli/cli_helpers.py
mince/cli/cli_parsing.py
mince/cli/cli_run.py
mince/cli/subcommands/__init__.py
mince/cli/subcommands/cd_command.py
mince/cli/subcommands/collect_command.py
mince/cli/subcommands/data_command.py
mince/cli/subcommands/dir_command.py
mince/cli/subcommands/docker_command.py
mince/cli/subcommands/kill_command.py
mince/cli/subcommands/ls_command.py
mince/cli/subcommands/register_command.py
mince/cli/subcommands/run_command.py
mince/cli/subcommands/spec_command.py
mince/cli/subcommands/unregister_command.py
mince/cli/subcommands/validate_command.py
mince/dashboards/__init__.py
mince/dashboards/dashboard_apps.py
mince/dashboards/dashboard_class.py
mince/dashboards/dashboard_classes.py
mince/dashboards/dashboard_inputs.py
mince/dashboards/dashboard_shortcuts.py
mince/dashboards/dashboard_state.py
mince/dashboards/dashboard_urls.py
mince/figures/__init__.py
mince/figures/raw_figures/__init__.py
mince/figures/raw_figures/line.py
mince/figures/raw_figures/stacked_bar.py
mince/figures/raw_figures/tree.py
mince/figures/reports/__init__.py
mince/figures/reports/changes.py
mince/figures/ui_figures/__init__.py
mince/figures/ui_figures/tree.py
mince/figures/ui_figures/timeseries/__init__.py
mince/figures/ui_figures/timeseries/timeseries_create.py
mince/figures/ui_figures/timeseries/timeseries_data.py
mince/figures/ui_figures/timeseries/timeseries_styles.py
mince/ops/__init__.py
mince/ops/collection/__init__.py
mince/ops/collection/collection_run.py
mince/ops/collection/collection_piecewise/README.md
mince/ops/collection/collection_piecewise/__init__.py
mince/ops/collection/collection_piecewise/piecewise_class.py
mince/ops/collection/collection_piecewise/piecewise_collector.py
mince/ops/collection/collection_piecewise/piecewise_io.py
mince/ops/collection/collection_piecewise/piecewise_summary.py
mince/ops/collection/collection_piecewise/piecewise_times.py
mince-0.2.4.dist-info/entry_points.txt
mince-0.2.4.dist-info/LICENSE-APACHE
mince-0.2.4.dist-info/LICENSE-MIT
mince-0.2.4.dist-info/WHEEL
mince-0.2.4.dist-info/METADATA
mince-0.2.4.dist-info/RECORD
